SimpleAES3/__init__.py
SimpleAES3/exceptions.py
SimpleAES3/version.py
SimpleAES3-1.0.6.dist-info/DESCRIPTION.rst
SimpleAES3-1.0.6.dist-info/METADATA
SimpleAES3-1.0.6.dist-info/RECORD
SimpleAES3-1.0.6.dist-info/WHEEL
SimpleAES3-1.0.6.dist-info/metadata.json
SimpleAES3-1.0.6.dist-info/top_level.txt
