Metadata-Version: 2.0
Name: SimpleAES3
Version: 1.0.6
Summary: SimpleAES: encryption and decryption for mere mortals. Port for python3
Home-page: https://github.com/NilayKulkarni/SimpleAES
Author: Nilay Kulkarni
Author-email: typhoscientic@gmail.com
License: BSD
Platform: any
Classifier: Development Status :: 4 - Beta
Classifier: Environment :: Console
Classifier: Environment :: MacOS X
Classifier: Environment :: Other Environment
Classifier: Environment :: Plugins
Classifier: Environment :: Web Environment
Classifier: Environment :: Win32 (MS Windows)
Classifier: Environment :: X11 Applications
Classifier: Intended Audience :: Developers
Classifier: Intended Audience :: Science/Research
Classifier: Intended Audience :: System Administrators
Classifier: License :: OSI Approved :: BSD License
Classifier: Natural Language :: English
Classifier: Operating System :: OS Independent
Classifier: Programming Language :: Python
Classifier: Topic :: Security :: Cryptography
Classifier: Topic :: Utilities
Requires-Dist: pycrypto
